MANIFEST.in
README.rst
setup.py
docs/HISTORY.txt
docs/LICENSE.GPL
docs/LICENSE.txt
ftw/__init__.py
ftw.collectionblock.egg-info/PKG-INFO
ftw.collectionblock.egg-info/SOURCES.txt
ftw.collectionblock.egg-info/dependency_links.txt
ftw.collectionblock.egg-info/entry_points.txt
ftw.collectionblock.egg-info/namespace_packages.txt
ftw.collectionblock.egg-info/not-zip-safe
ftw.collectionblock.egg-info/requires.txt
ftw.collectionblock.egg-info/top_level.txt
ftw/collectionblock/__init__.py
ftw/collectionblock/configure.zcml
ftw/collectionblock/hooks.py
ftw/collectionblock/lawgiver.zcml
ftw/collectionblock/permissions.zcml
ftw/collectionblock/resources.zcml
ftw/collectionblock/testing.py
ftw/collectionblock/utils.py
ftw/collectionblock/Extensions/__init__.py
ftw/collectionblock/Extensions/install.py
ftw/collectionblock/browser/__init__.py
ftw/collectionblock/browser/block_view.py
ftw/collectionblock/browser/configure.zcml
ftw/collectionblock/browser/resources/collectionblock.js
ftw/collectionblock/browser/resources/styles.scss
ftw/collectionblock/browser/templates/block_view.pt
ftw/collectionblock/browser/templates/listing.pt
ftw/collectionblock/contents/__init__.py
ftw/collectionblock/contents/collectionblock.py
ftw/collectionblock/contents/configure.zcml
ftw/collectionblock/contents/interfaces.py
ftw/collectionblock/locales/ftw.collectionblock.pot
ftw/collectionblock/locales/plone.pot
ftw/collectionblock/locales/de/LC_MESSAGES/ftw.collectionblock.po
ftw/collectionblock/locales/de/LC_MESSAGES/plone.po
ftw/collectionblock/profiles/default/jsregistry.xml
ftw/collectionblock/profiles/default/metadata.xml
ftw/collectionblock/profiles/default/propertiestool.xml
ftw/collectionblock/profiles/default/rolemap.xml
ftw/collectionblock/profiles/default/types.xml
ftw/collectionblock/profiles/default/workflows.xml
ftw/collectionblock/profiles/default/types/Plone_Site.xml
ftw/collectionblock/profiles/default/types/ftw.collectionblock.CollectionBlock.xml
ftw/collectionblock/profiles/default/types/ftw.simplelayout.ContentPage.xml
ftw/collectionblock/profiles/default_plone5/metadata.xml
ftw/collectionblock/profiles/default_plone5/registry.xml
ftw/collectionblock/profiles/default_plone5/rolemap.xml
ftw/collectionblock/profiles/default_plone5/types.xml
ftw/collectionblock/profiles/default_plone5/workflows.xml
